pyratbay/__init__.py
pyratbay/__main__.py
pyratbay/driver.py
pyratbay/version.py
pyratbay/atmosphere/__init__.py
pyratbay/atmosphere/atmosphere.py
pyratbay/atmosphere/qscaling.py
pyratbay/atmosphere/vmr_scaling.py
pyratbay/atmosphere/alkali/__init__.py
pyratbay/atmosphere/alkali/alkali.py
pyratbay/atmosphere/clouds/__init__.py
pyratbay/atmosphere/clouds/gray.py
pyratbay/atmosphere/rayleigh/__init__.py
pyratbay/atmosphere/rayleigh/rayleigh.py
pyratbay/atmosphere/tmodels/__init__.py
pyratbay/atmosphere/tmodels/tmodels.py
pyratbay/constants/__init__.py
pyratbay/constants/astrophysical_constants.py
pyratbay/constants/code_constants.py
pyratbay/constants/constants.py
pyratbay/data/AsplundEtal2009.txt
pyratbay/data/atoms.dat
pyratbay/data/isotopes.dat
pyratbay/data/molecules.dat
pyratbay/data/tips_2021.pkl
pyratbay/data/CIA/CIA_Borysow_H2H2_0060-7000K_0.6-500um.dat
pyratbay/data/CIA/CIA_Borysow_H2He_0050-3000K_0.3-030um.dat
pyratbay/data/CIA/CIA_Borysow_H2He_1000-7000K_0.5-400um.dat
pyratbay/data/filters/spitzer_irac1_sa.dat
pyratbay/data/filters/spitzer_irac2_sa.dat
pyratbay/data/filters/spitzer_irac3_sa.dat
pyratbay/data/filters/spitzer_irac4_sa.dat
pyratbay/data/filters/spitzer_mips24.dat
pyratbay/io/__init__.py
pyratbay/io/io.py
pyratbay/lib/_alkali.cpython-39-darwin.so
pyratbay/lib/_blackbody.cpython-39-darwin.so
pyratbay/lib/_extcoeff.cpython-39-darwin.so
pyratbay/lib/_indices.cpython-39-darwin.so
pyratbay/lib/_pt.cpython-39-darwin.so
pyratbay/lib/_simpson.cpython-39-darwin.so
pyratbay/lib/_spline.cpython-39-darwin.so
pyratbay/lib/_trapz.cpython-39-darwin.so
pyratbay/lib/cutils.cpython-39-darwin.so
pyratbay/lib/vprofile.cpython-39-darwin.so
pyratbay/opacity/__init__.py
pyratbay/opacity/lread.py
pyratbay/opacity/broadening/__init__.py
pyratbay/opacity/broadening/broadening.py
pyratbay/opacity/linelist/__init__.py
pyratbay/opacity/linelist/driver.py
pyratbay/opacity/linelist/exomol.py
pyratbay/opacity/linelist/hitran.py
pyratbay/opacity/linelist/pands.py
pyratbay-1.1.6.dist-info/LICENSE
pyratbay-1.1.6.dist-info/METADATA
pyratbay-1.1.6.dist-info/WHEEL
pyratbay-1.1.6.dist-info/entry_points.txt
pyratbay-1.1.6.dist-info/top_level.txt
pyratbay-1.1.6.dist-info/RECORD
