Metadata-Version: 2.1
Name: pyratbay
Version: 1.1.6
Summary: Python Radiative Transfer in a Bayesian Framework.
Home-page: https://github.com/pcubillos/pyratbay
Author: Patricio Cubillos
Author-email: patricio.cubillos@oeaw.ac.at
License: GPLv2
Platform: UNKNOWN
Requires-Dist: numpy (>=1.15.1)
Requires-Dist: scipy (>=1.4.1)
Requires-Dist: matplotlib (>=3.3.4)
Requires-Dist: mc3 (>=3.0.7)
Requires-Dist: chemcat (>=0.3.1)
